{
    "baseVideoDuration": 14,
    "baseVideoId": "vO9Qijeiznw",
    "cut": [
        {
            "with": {
                "id": "vO9Qijeiznw",
                "begin": 0,
                "duration": 4,
                "end": 4
            },
            "begin": 0,
            "duration": 2,
            "end": 2
        }
    ],
    "clip": [
        {
            "id": "vO9Qijeiznw",
            "begin": 0,
            "duration": 4,
            "end": 4
        },
        {
            "begin": 2,
            "duration": 12,
            "end": 14,
            "id": "vO9Qijeiznw"
        }
    ]
}