{
    "baseVideoDuration": 242,
    "baseVideoId": "7cNaqQ5sqgo",
    "cut": [
        {
            "with": {
                "id": "7cNaqQ5sqgo",
                "begin": 0,
                "duration": 0,
                "end": 0
            },
            "begin": 0,
            "duration": 10.899966,
            "end": 10.899966
        }
    ],
    "clip": [
        {
            "id": "7cNaqQ5sqgo",
            "begin": 0,
            "duration": 0,
            "end": 0
        },
        {
            "begin": 10.899966,
            "duration": 231.100034,
            "end": 242,
            "id": "7cNaqQ5sqgo"
        }
    ]
}